[
  {
    "line": 2,
    "elements": [
      {
        "start_timestamp": "2021-01-24T12:31:42.387Z",
        "line": 12,
        "name": "To validate the HTTP get method",
        "description": "",
        "id": "to-validate-different-apis-for-different-http-methods;to-validate-the-http-get-method;;2",
        "type": "scenario",
        "keyword": "Scenario Outline",
        "steps": [
          {
            "result": {
              "duration": 15000000,
              "status": "passed"
            },
            "line": 6,
            "name": "user is given with the get method to be automated",
            "match": {
              "location": "StepDefinitions.APISteps.user_is_given_with_the_get_method_to_be_automated()"
            },
            "keyword": "Given "
          },
          {
            "result": {
              "duration": 5699000000,
              "status": "passed"
            },
            "line": 7,
            "name": "hit the get method",
            "match": {
              "location": "StepDefinitions.APISteps.hit_the_get_method()"
            },
            "keyword": "When "
          },
          {
            "result": {
              "status": "passed"
            },
            "line": 8,
            "name": "validate that the user should get response with the 200",
            "match": {
              "arguments": [
                {
                  "val": "200",
                  "offset": 52
                }
              ],
              "location": "StepDefinitions.APISteps.validate_that_the_user_should_get_response_with_the(java.lang.Integer)"
            },
            "keyword": "Then "
          }
        ],
        "tags": [
          {
            "name": "@APITest"
          },
          {
            "name": "@get"
          }
        ]
      }
    ],
    "name": "To validate different APIs for different HTTP methods",
    "description": "",
    "id": "to-validate-different-apis-for-different-http-methods",
    "keyword": "Feature",
    "uri": "file:src/test/resources/Feature/APIFeature.feature",
    "tags": [
      {
        "name": "@APITest",
        "type": "Tag",
        "location": {
          "line": 1,
          "column": 1
        }
      }
    ]
  }
]